nomenclate/__init__.py
nomenclate/core/__init__.py
nomenclate/core/configurator.py
nomenclate/core/errors.py
nomenclate/core/file_utils.py
nomenclate/core/formatter.py
nomenclate/core/nameparser.py
nomenclate/core/nomenclature.py
nomenclate/core/processing.py
nomenclate/core/renderers.py
nomenclate/core/rendering.py
nomenclate/core/template/env.yml
nomenclate/core/tokens.py
nomenclate/core/tools.py
nomenclate/settings.py
nomenclate/version.py
nomenclate-2.6.5.dist-info/WHEEL
nomenclate-2.6.5.dist-info/METADATA
nomenclate-2.6.5.dist-info/RECORD
