Metadata-Version: 2.1
Name: nomenclate
Version: 2.6.5
Summary: A tool set for automating and generating strings based on arbitrary user-defined naming conventions.
Home-page: https://nomenclate.andresmweber.com
License: MIT
Keywords: naming,conventions,labels,config,convention,name,parsing,parse
Author: Andres Weber
Author-email: andresmweber@gmail.com
Requires-Python: >=3.6,<4.0
Classifier: Development Status :: 4 - Beta
Classifier: License :: OSI Approved :: MIT License
Classifier: Natural Language :: English
Classifier: Operating System :: MacOS :: MacOS X
Classifier: Operating System :: Microsoft :: Windows
Classifier: Operating System :: POSIX :: Linux
Classifier: Operating System :: Unix
Classifier: Programming Language :: Python :: 3
Classifier: Programming Language :: Python :: 3.6
Classifier: Programming Language :: Python :: 3.7
Classifier: Programming Language :: Python :: 3.8
Classifier: Programming Language :: Python :: 3.9
Classifier: Topic :: Documentation :: Sphinx
Classifier: Topic :: Multimedia :: Graphics :: 3D Modeling
Provides-Extra: autodoc
Requires-Dist: PyYAML (>=5.4.1,<6.0.0)
Requires-Dist: python-dateutil (>=2.8.1,<3.0.0)
Requires-Dist: toml (>=0.10.2,<0.11.0)
Project-URL: Documentation, https://nomenclate.readthedocs.io/en/latest/
Project-URL: Repository, https://github.com/AndresMWeber/Nomenclate
